ehandler/__init__.py
ehandler/base.py
ehandler/http/__init__.py
ehandler/http/api.py
ehandler/http/client.py
ehandler/logging/__init__.py
ehandler/logging/base.py
ehandler/logging/handler.py
ehandler/models/__init__.py
ehandler/models/base.py
ehandler/models/log.py
ehandler/models/log_gcp.py
ehandler/models/utils.py
ehandler/parsers.py
ehandler/settings.py
ehandler/utils.py
ehandler-0.5.1.dist-info/WHEEL
ehandler-0.5.1.dist-info/METADATA
ehandler-0.5.1.dist-info/RECORD
