Metadata-Version: 2.1
Name: ehandler
Version: 0.5.1
Summary: Utility to create exception handlers in FastAPI in a flexible and standard way
Author: Alan Vazquez
Author-email: alan@trii.co
Requires-Python: >=3.10,<4.0
Classifier: Programming Language :: Python :: 3
Classifier: Programming Language :: Python :: 3.10
Classifier: Programming Language :: Python :: 3.11
Requires-Dist: aiohttp (>=3.8.0)
Requires-Dist: fastapi (>=0.70)
Requires-Dist: orjson (>=3.8.0)
Requires-Dist: pydantic (>=1.0)
Requires-Dist: python-dotenv (>=0.10.0)
